ezetl/__init__.py
ezetl/etl_task.py
ezetl/data_models/__init__.py
ezetl/data_models/akshare_models.py
ezetl/data_models/base_db_sql.py
ezetl/data_models/base_db_table.py
ezetl/data_models/ccxt_models.py
ezetl/data_models/clickhouse_table.py
ezetl/data_models/elasticsearch_index.py
ezetl/data_models/file_models.py
ezetl/data_models/hdfs_models.py
ezetl/data_models/hive_models.py
ezetl/data_models/http_models.py
ezetl/data_models/ixdb_models.py
ezetl/data_models/kafka_topic.py
ezetl/data_models/minio_models.py
ezetl/data_models/mongo_models.py
ezetl/data_models/mysql_binlog.py
ezetl/data_models/mysql_table.py
ezetl/data_models/neo4j_models.py
ezetl/data_models/oracle_models.py
ezetl/data_models/pgsql_models.py
ezetl/data_models/prometheus_models.py
ezetl/data_models/redis_models.py
ezetl/data_models/sqlserver_models.py
ezetl/examples/__init__.py
ezetl/examples/etl_demos/__init__.py
ezetl/examples/etl_demos/binlog2kafka.py
ezetl/examples/etl_demos/csv2csv.py
ezetl/examples/etl_demos/csv2mysql.py
ezetl/examples/etl_demos/kafka2es.py
ezetl/examples/etl_demos/kafka2ixdb.py
ezetl/examples/etl_demos/mysql2es.py
ezetl/examples/etl_demos/mysql2kafka.py
ezetl/examples/etl_demos/mysql2mongodb.py
ezetl/examples/etl_demos/mysql2n4j.py
ezetl/examples/etl_task/__init__.py
ezetl/examples/etl_task/batch_task_demo.py
ezetl/examples/etl_task/etl_process_task_demo.py
ezetl/examples/etl_task/stream_task_demo.py
ezetl/examples/reader/__init__.py
ezetl/examples/reader/read_csv.py
ezetl/examples/reader/read_es.py
ezetl/examples/reader/read_kafka.py
ezetl/examples/reader/read_mongodb.py
ezetl/examples/reader/read_mysql.py
ezetl/examples/reader/read_mysql_binlog.py
ezetl/examples/reader/read_n4j.py
ezetl/libs/__init__.py
ezetl/libs/es.py
ezetl/libs/hdfs.py
ezetl/libs/ixdb.py
ezetl/libs/kafka_utils.py
ezetl/libs/n4j.py
ezetl/libs/prometheus.py
ezetl/transform_algs/__init__.py
ezetl/transform_algs/content_algs.py
ezetl/transform_algs/count_algs.py
ezetl/transform_algs/filter_algs.py
ez_etl-1.1.6.dist-info/LICENSE
ez_etl-1.1.6.dist-info/METADATA
ez_etl-1.1.6.dist-info/WHEEL
ez_etl-1.1.6.dist-info/top_level.txt
ez_etl-1.1.6.dist-info/RECORD
