Metadata-Version: 2.1
Name: ez-etl
Version: 1.1.6
Summary: ez-etl is an open-source Extract, Transform, load (ETL) library written in Python. Just configure a dict to read data from various data sources. Use code or built-in conversion algorithms to transform the data into the target data format， and write it to the target data source. 
Author: Xu Wei
Author-email: 1013104194@qq.com
License: Apache License 2.0
Keywords: etl,extract,transform,load,excel,csv,mysql,kafka,elasticsearch,neo4j,influxdb,mongodb,clickhouse
License-File: LICENSE
Requires-Dist: requests
Requires-Dist: sshtunnel
Requires-Dist: python-dateutil
Requires-Dist: pandas (>=1.0.0)
Requires-Dist: openpyxl
Requires-Dist: xlrd
Requires-Dist: minio (==7.1.1)
Requires-Dist: sqlalchemy (>=1.2.0)
Requires-Dist: pymysql
Requires-Dist: redis
Requires-Dist: elasticsearch (>=7.15.2)
Requires-Dist: kafka-python (==2.0.2)
Requires-Dist: mysql-replication (==0.27)
Provides-Extra: all
Requires-Dist: xorbits (==0.3.2) ; extra == 'all'
Requires-Dist: pyarrow (>=5.0.0) ; extra == 'all'
Requires-Dist: akshare ; extra == 'all'
Requires-Dist: ccxt ; extra == 'all'
Requires-Dist: psycopg2-binary ; extra == 'all'
Requires-Dist: pymssql ; extra == 'all'
Requires-Dist: cx-oracle ; extra == 'all'
Requires-Dist: clickhouse-sqlalchemy ; extra == 'all'
Requires-Dist: thrift ; extra == 'all'
Requires-Dist: thrift-sasl ; extra == 'all'
Requires-Dist: pyhive ; extra == 'all'
Requires-Dist: py2neo ; extra == 'all'
Requires-Dist: prometheus-api-client ; extra == 'all'
Requires-Dist: mongoengine ; extra == 'all'
Requires-Dist: influxdb (==5.3.1) ; extra == 'all'
Provides-Extra: xorbits
Requires-Dist: xorbits (==0.3.2) ; extra == 'xorbits'
Requires-Dist: pyarrow (>=5.0.0) ; extra == 'xorbits'
